{"name":"Curso mejorandola basico","tagline":"Codigo que se va elaborando durante el curso de mejorandola","body":"<!DOCTYPE html>\t\r\n<html>\r\n<head>\r\n\t<meta charset=\"UTF-8\">\r\n\t<script src=\"http://ajax.googleapis.com/ajax/libs/jquery/1.11.1/jquery.min.js\"></script>\r\n\t<script  src=\"js/miniplay.js\"></script>\r\n\t\r\n\t<title>Minu-Juego</title>\r\n\t\r\n<link rel=\"stylesheet\" type=\"text/css\" href=\"css/estilo.css\">\r\n<link rel=\"stylesheet\" type=\"text/css\" href=\"css/fonts.css\">\r\n\t\r\n</head>\r\n\r\n<body>\r\n\t<div id=\"colores\"></div>\r\n\t<a href=\"https://github.com/ulisescerv91/\" target=\"_blank\"  id=\"titulo1\">BY: Ulises_cervantes</a>\r\n\t<center><p id=\"titulo2\">Piedra - Papel-Tijeras-Lagarto-Spock</p></center>\r\n\t<div id=\"menu\"><span class=\"botones\" id=\"jugar\" type=\"button\">jugar</span><span class=\"botones\" id=\"ver_reglas\">reglas</span></div>\r\n\t\r\n\r\n\t<div id=\"opcionesdiv\">\r\n\t\t<center><p id=\"elige\">Selecciona una opcion:</p></center>\r\n\t\t<center><img src=\"pictures/reglas.PNG\" id=\"img_reglas\"><br></center>\r\n\t\t<img id=\"piedra\"class=\"opciones\" onclick=\"jugar(0)\"  src=\"pictures/Piedra.PNG\" title=\"Piedra\">\r\n\t\t<img  id=\"papel\"class=\"opciones\" onclick=\"jugar(1)\" src=\"pictures/Papel.PNG\" title=\"Papel\">\r\n\t\t<img id=\"tijeras\" class=\"opciones\"  onclick=\"jugar(2)\"src=\"pictures/Tijeras.PNG\" title=\"tijera\">\r\n\t\t<img id=\"lagarto\" class=\"opciones\"  onclick=\"jugar(3)\"src=\"pictures/Lagarto.PNG\" title=\"lagarto\">\r\n\t\t<img id=\"spock\" class=\"opciones\"  onclick=\"jugar(4)\" src=\"pictures/Spock.PNG\"title=\"Spock\">\r\n\t\t<label id=\"l_piedra\" class=\"etiquetas\">piedra</label>\r\n\t\t<label id=\"l_papel\" class=\"etiquetas\">papel</label>\r\n\t\t<label id=\"l_tijeras\" class=\"etiquetas\">tijeras</label>\r\n\t\t<label id=\"l_lagarto\" class=\"etiquetas\">lagarto</label>\r\n\t\t<label id=\"l_spock\" class=\"etiquetas\">spock</label>\r\n\t\r\n\r\n\r\n\t</div>\r\n\t<div id=\"divreglas\">\r\n\t\t<center><p id=\"sheldon\">Reglas segun Sheldon Cooper</p></center>\r\n\t\t<center><iframe id=\"video\" width=\"560\" height=\"315\" src=\"//www.youtube.com/embed/S5eLybE03gc\" frameborder=\"0\" allowfullscreen></iframe></center>\r\n\t</div>\r\n\r\n\t<div id=\"vs\">\r\n\t\t<center><span id=\"tu\">Tu</span><span id=\"pc\">Sheldon</span></center>\r\n\t\t<center><img src=\"pictures/vs.PNG\" id=\"vs_img\"></center>\r\n\t\t<img  class=\"resul\" id=\"opc_user\"src=\"\">\r\n\t\t<img class=\"resul\" id=\"opc_pc\" src=\"\">\r\n\t\t<img src=\"\"  id=\"img_sheldon\"><br>\r\n\t\t<span id=\"again\">JUGAR DE NUEVO!!</span>\r\n\t</div>\r\n\t<p id=\"resultado\"></p>\r\n\t\t\r\n\t\r\n\r\n</body>\r\n</html>\r\n","google":"","note":"Don't delete this file! It's used internally to help with page regeneration."}